LICENSE.txt
MANIFEST.in
README.md
pyproject.toml
setup.cfg
setup.py
version.txt
mint/__init__.py
mint/__init__.py.in
mint/grid.py
mint/polyline_integral.py
mint/regrid_edges.py
mint/vector_interp.py
mint/tests/__init__.py
mint/tests/test_grid.py
mint/tests/test_polyline_integral.py
mint/tests/test_regrid_edges.py
mint/tests/test_vector_interp.py
python_mint.egg-info/PKG-INFO
python_mint.egg-info/SOURCES.txt
python_mint.egg-info/dependency_links.txt
python_mint.egg-info/not-zip-safe
python_mint.egg-info/requires.txt
python_mint.egg-info/top_level.txt
src/CmdLineArgParser.cpp
src/CmdLineArgParser.h
src/GrExprAdaptor.cpp
src/GrExprAdaptor.h
src/GrExprParser.cpp
src/GrExprParser.h
src/MvFunctors.h
src/MvMat_double.cpp
src/MvMatrix.h
src/MvVector.cpp
src/MvVector.h
src/mntCellLocator.cpp
src/mntCellLocator.h
src/mntCmdLineArgParser.cpp
src/mntCmdLineArgParser.h
src/mntDots.cpp
src/mntDots.h
src/mntGrid.cpp
src/mntGrid.h
src/mntLatLon.cpp
src/mntLatLon.h
src/mntLineLineIntersector.h
src/mntLineTriangleIntersector.cpp
src/mntLineTriangleIntersector.h
src/mntMatMxN.cpp
src/mntMatMxN.h
src/mntMultiArrayIter.cpp
src/mntMultiArrayIter.h
src/mntNcAttributes.cpp
src/mntNcAttributes.h
src/mntNcDimensions.cpp
src/mntNcDimensions.h
src/mntNcFieldRead.cpp
src/mntNcFieldRead.h
src/mntNcFieldWrite.cpp
src/mntNcFieldWrite.h
src/mntPolylineIntegral.cpp
src/mntPolylineIntegral.h
src/mntPolylineParser.cpp
src/mntPolylineParser.h
src/mntPolysegmentIter.cpp
src/mntPolysegmentIter.h
src/mntQuadEdgeIter.cpp
src/mntQuadEdgeIter.h
src/mntRegridAxis.cpp
src/mntRegridAxis.h
src/mntRegridEdges.cpp
src/mntRegridEdges.h
src/mntUgrid2D.cpp
src/mntUgrid2D.h
src/mntVecN.cpp
src/mntVecN.h
src/mntVectorInterp.cpp
src/mntVectorInterp.h
src/mntWeights.cpp
src/mntWeights.h
src/vmtCellLocator.cpp
src/vmtCellLocator.h