Metadata-Version: 2.1
Name: python-mint
Version: 1.15.4
Summary: Mimetic INTerpolation on the Sphere
Home-page: https://github.com/pletzer/mint
Author: Alexander Pletzer
Author-email: alexander.pletzer@nesi.org.nz
License: Zero-Clause BSD
Project-URL: code, https://github.com/pletzer/mint
Project-URL: issues, https://github.com/pletzer/mint/issues
Keywords: mimetic,regrid,interpolate,sphere
Platform: UNKNOWN
Classifier: License :: OSI Approved :: BSD License
Classifier: Programming Language :: C++
Classifier: Programming Language :: Fortran
Classifier: Programming Language :: Python
Classifier: Programming Language :: Python :: 3 :: Only
Classifier: Programming Language :: Python :: 3.6
Classifier: Programming Language :: Python :: 3.7
Classifier: Programming Language :: Python :: 3.8
Classifier: Topic :: Scientific/Engineering :: Atmospheric Science
Requires-Python: <3.9,>3.6
